rtl/mem/dmem.sv
module dmem(
    input logic clk,
    
    input logic mem_read,
    input logic mem_write,
    input logic [2:0] mem_width,

    input logic [31:0] addr,
    input logic [31:0] write_data,
    output logic [31:0] read_data
);
    import riscv_pkg::*;

    logic [3:0][7:0] ram [0:2047];

    logic [10:0] addr_word_index;
    logic [1:0]  addr_byte_offset;
    assign addr_word_index  = addr[12:2];
    assign addr_byte_offset = addr[1:0];

    logic [1:0] mem_width_select;
    logic       mem_width_unsigned;
    assign mem_width_select   = mem_width[1:0];
    assign mem_width_unsigned = mem_width[2];

    logic mem_active, mem_write_active, mem_read_active;
    assign mem_active = (addr < 32'h2000); // valid range: 0x0000 - 0x1FFF (2048 words * 4 bytes)
    assign mem_write_active = mem_active & mem_write;
    assign mem_read_active = mem_active & mem_read;
    
    // device selector for MMIO (memory valid from 0x00000000 - 0x0000FFFF theoretically, 0x00000000 - 0x00000800 with current implementation)
    // for UART peripheral, for example, mem_active would be addr[31:16] == 4'h0001, giving it 65535 memory addresses for its stuff

    // write path
    always_ff @(negedge clk) begin
        if (mem_write_active) begin
            casez (mem_width)
                MEM_WIDTH_WORD: begin
                    ram[addr_word_index] <= write_data;
                end

                MEM_WIDTH_HALFWORD: begin
                    if (addr_byte_offset[1])    ram[addr_word_index][3:2] <= write_data[15:0];
                    else                        ram[addr_word_index][1:0] <= write_data[15:0];
                end

                MEM_WIDTH_BYTE: begin
                    ram[addr_word_index][addr_byte_offset] <= write_data[7:0];
                end

                default: begin end
            endcase
        end
    end

    // read path
    logic [3:0][7:0] raw_word;
    assign raw_word = ram[addr_word_index];

    always_comb begin
        read_data = 32'b0;
        if (mem_read_active) begin
            casez (mem_width)
                MEM_WIDTH_WORD: begin
                    read_data = raw_word;
                end

                MEM_WIDTH_HALFWORD: begin
                    if (addr_byte_offset[1]) begin
                        read_data = {{16{mem_width_unsigned ? 1'b0 : raw_word[3][7]}}, raw_word[3:2]};
                    end else begin
                        read_data = {{16{mem_width_unsigned ? 1'b0 : raw_word[1][7]}}, raw_word[1:0]};
                    end
                end

                MEM_WIDTH_BYTE: begin
                    read_data = {{24{mem_width_unsigned ? 1'b0 : raw_word[addr_byte_offset][7]}}, raw_word[addr_byte_offset]};
                end

                default: read_data = 32'b0;
            endcase
        end
    end
endmodule

rtl/mem/imem.sv
module imem(
    input logic [31:0] addr,
    output logic [31:0] data
);
    logic [31:0] mem [0:1023];

    initial begin
        $readmemh("program.hex", mem);
    end

    assign data = mem[addr[11:2]];
endmodule

rtl/core/alu.sv
module alu(
    input logic [31:0] alu_in_a,
    input logic [31:0] alu_in_b,
    input logic [3:0] alu_op,

    output logic [31:0] alu_out,
    output logic zero               // 0 = alu output not zero, 1 = alu output zero
);
    import riscv_pkg::*;
    
    always_comb begin
        alu_out = 32'b0;

        case (alu_op)
            // arithmetic 
            ALU_ADD: alu_out = alu_in_a + alu_in_b;
            ALU_SUB: alu_out = alu_in_a - alu_in_b;

            // bitwise 
            ALU_OR:  alu_out = alu_in_a | alu_in_b;
            ALU_AND: alu_out = alu_in_a & alu_in_b;
            ALU_XOR: alu_out = alu_in_a ^ alu_in_b;

            // shift
            ALU_SLL: alu_out = alu_in_a << alu_in_b[4:0];
            ALU_SRL: alu_out = alu_in_a >> alu_in_b[4:0];
            ALU_SRA: alu_out = alu_in_a >>> alu_in_b[4:0];

            // comparison
            ALU_SLT: begin
                if (signed'(alu_in_a) < signed'(alu_in_b)) alu_out = 32'b1;
                else                                       alu_out = 32'b0;
            end
            ALU_SLTU: begin
                if (alu_in_a < alu_in_b) alu_out = 32'b1;
                else                     alu_out = 32'b0;
            end

            // helpers
            ALU_COPY_B: alu_out = alu_in_b;

            default: alu_out = 32'b0;
        endcase
    end
    assign zero = (alu_out == 32'b0);
endmodule

rtl/core/imm_dec.sv
module imm_dec(
    input logic [2:0] imm_type,
    input logic [31:0] inst,
    output logic [31:0] imm
);
    import riscv_pkg::*;
    
    always_comb begin
        case (imm_type)
            IMM_I:      imm = {{21{inst[31]}}, inst[30:25], inst[24:21], inst[20]};
            IMM_S:      imm = {{21{inst[31]}}, inst[30:25], inst[11:8], inst[7]};
            IMM_B:      imm = {{20{inst[31]}}, inst[7], inst[30:25], inst[11:8], 1'b0};
            IMM_U:      imm = {inst[31], inst[30:20], inst[19:12], 12'b0};
            IMM_J:      imm = {{12{inst[31]}}, inst[19:12], inst[20], inst[30:25], inst[24:21], 1'b0};
            IMM_NONE:   imm = 32'b0; // Explicitly zero out for no immediate (R-type instructions)
            default:    imm = 32'b0;
        endcase
    end
endmodule

rtl/core/inst_dec.sv
module inst_dec(
    input logic [31:0] inst,            // input instruction

    output logic [4:0] rs1,             // source register 1
    output logic [4:0] rs2,             // source register 2
    output logic [4:0] rd,              // destination register

    output logic [31:0] imm,            // immediate value
    
    // control signals
    output logic rd_write,              // write alu result to destination register

    output logic [2:0] branch_op,       // type of branching to perform
    output logic [2:0] mem_width,       // width of memory access

    output logic [3:0] alu_op,          // alu operation to perform
    output logic alu_src_a,             // alu operand one source, 0 = rs1, 1 = pc
    output logic alu_src_b,             // alu operand two source, 0 = rs2, 2 = imm

    output logic mem_read,              // read value at address from alu result (rs1 + imm) to rd
    output logic mem_write,             // write value from rs2 at mem address from alu result (rs1 + imm)
    output logic branch,                // enable branching (to alu result) if cond. met
    output logic jump,                  // enable jumping (to alu result) if cond. met
    output logic system_halt            // permanently stop the system
);
    import riscv_pkg::*;

    logic [6:0] opcode;
    logic [2:0] funct3; 
    logic [6:0] funct7; 

    assign opcode = inst[6:0];
    assign funct3 = inst[14:12];
    assign funct7 = inst[31:25];

    assign rs1 = inst[19:15];
    assign rs2 = inst[24:20];
    assign rd = inst[11:7];

    logic [2:0] imm_type;
    always_comb begin
        rd_write    = 1'b0;
        alu_op      = ALU_ADD;
        branch_op   = BRANCH_BEQ;
        mem_width   = MEM_WIDTH_WORD;
        alu_src_a   = 1'b0;
        alu_src_b   = 1'b0;
        mem_read    = 1'b0;
        mem_write   = 1'b0;
        branch      = 1'b0;
        jump        = 1'b0;
        imm_type    = IMM_NONE;
        system_halt = 1'b0;

        case (opcode)
            OP_REG: begin
                rd_write = 1'b1;
                alu_src_a = 1'b0;
                alu_src_b = 1'b0;
                imm_type = IMM_NONE;
                alu_op = alu_op_e'({ funct7[5], funct3 });
            end

            OP_REG_IMM: begin 
                rd_write = 1'b1;
                alu_src_a = 1'b0;
                alu_src_b = 1'b1;
                imm_type = IMM_I;

                if ((funct3 == 3'b001) || (funct3 == 3'b101))
                    alu_op = alu_op_e'({ funct7[5], funct3 });
                else
                    alu_op = alu_op_e'({1'b0, funct3});
            end

            OP_LUI: begin
                rd_write = 1'b1;
                alu_src_a = 1'b0;
                alu_src_b = 1'b1;
                imm_type = IMM_U;
                alu_op = ALU_COPY_B;
            end

            OP_AUIPC: begin
                rd_write = 1'b1;
                alu_src_a = 1'b1;
                alu_src_b = 1'b1;
                imm_type = IMM_U;
                alu_op = ALU_ADD;
            end

            OP_LOAD: begin
                rd_write = 1'b1;
                alu_src_a = 1'b0;
                alu_src_b = 1'b1;
                imm_type = IMM_I;
                alu_op = ALU_ADD;
                mem_read = 1'b1;
                mem_width = mem_width_e'(funct3);
            end

            OP_STORE: begin
                rd_write = 1'b0;
                alu_src_a = 1'b0;
                alu_src_b = 1'b1;
                imm_type = IMM_S;
                alu_op = ALU_ADD;
                mem_write = 1'b1;
                mem_width = mem_width_e'(funct3);
            end

            OP_BRANCH: begin
                rd_write = 1'b0;
                alu_src_a = 1'b1;
                alu_src_b = 1'b1;
                imm_type = IMM_B;
                alu_op = ALU_ADD;
                branch = 1'b1;
                branch_op = branch_type_e'(funct3);
            end

            OP_JAL: begin
                rd_write = 1'b1;
                alu_src_a = 1'b1;
                alu_src_b = 1'b1;
                imm_type = IMM_J;
                alu_op = ALU_ADD;
                jump = 1'b1;
            end

            OP_JALR: begin
                rd_write = 1'b1;
                alu_src_a = 1'b0;
                alu_src_b = 1'b1;
                imm_type = IMM_I;
                alu_op = ALU_ADD;
                jump = 1'b1;
            end

            OP_MISC_MEM: begin // handle FENCE instructions. single-cycle cpu needs no extra work here.
                imm_type = IMM_I;
                rd_write = 1'b0;
                mem_write = 1'b0;
            end

            OP_SYSTEM: begin
                if (inst == 32'h00000073 || inst == 32'h00100073) begin
                    system_halt = 1'b1;
                end
            end

            default: begin end
        endcase
    end

    imm_dec immediate_decoder(
        .imm_type(imm_type),
        .inst(inst),
        .imm(imm)
    );
endmodule

rtl/core/pc.sv
module pc(
    input logic clk,
    input logic rst,

    input logic pc_jmp_en, // 0 = pc inc by 32'd4, 1 = pc jmp to pc_jmp_target
    input logic [31:0] pc_jmp_target,

    output logic [31:0] pc_curr
);
    localparam logic [31:0] BOOT_ADDR = 32'h0;

    logic [31:0] pc_next;
    assign pc_next = (pc_jmp_en ? pc_jmp_target : (pc_curr + 32'd4));

    always_ff @(posedge clk) begin
        if (rst)
            pc_curr <= BOOT_ADDR;
        else
            pc_curr <= pc_next;
    end
endmodule

rtl/core/bcu.sv
module bcu(
    input logic [2:0] branch_op,
    input logic [31:0] rv1,
    input logic [31:0] rv2,

    output logic branch
);
    import riscv_pkg::*;

    always_comb begin
        case (branch_op)
            BRANCH_BEQ: branch = (rv1 == rv2);                      // BEQ
            BRANCH_BNE: branch = (rv1 != rv2);                      // BNE

            BRANCH_BLT: branch = (signed'(rv1) < signed'(rv2));     // BLT
            BRANCH_BGE: branch = (signed'(rv1) >= signed'(rv2));    // BGE

            BRANCH_BLTU: branch = (rv1 < rv2);                       // BLTU
            BRANCH_BGEU: branch = (rv1 >= rv2);                      // BGEU

            default: branch = 1'b0;
        endcase
    end
endmodule

rtl/core/reg_file.sv
module reg_file(
    input logic clk,
    input logic rst,

    input logic [4:0] rd,
    input logic [4:0] rs1,
    input logic [4:0] rs2,

    input logic rd_write,
    input logic [31:0] rd_write_val,

    output logic [31:0] rv1,
    output logic [31:0] rv2
);
    logic [31:0] registers [0:31];

    always_comb begin
        rv1 = (rs1 == 5'b0) ? 32'b0 : registers[rs1];
        rv2 = (rs2 == 5'b0) ? 32'b0 : registers[rs2];
    end

    always_ff @(negedge clk) begin
        if (rd_write && rd != 5'b0)
            registers[rd] <= rd_write_val;
    end
endmodule

rtl/core/cpu_top.sv
module cpu_top(
    input logic clk,
    input logic rst,

    output logic [31:0] imem_addr,
    input logic [31:0] imem_data,

    output logic [31:0] dmem_addr,
    output logic dmem_read,
    output logic dmem_write,
    input logic [31:0] dmem_rdata,
    output logic [31:0] dmem_wdata,
    output logic [2:0] dmem_width,

    output logic [31:0] debug_pc,
    output logic simulation_end
);
    import riscv_pkg::*;

    logic [31:0] pc, imm, rv1, rv2, alu_out, rd_write_val;
    logic [4:0] rs1, rs2, rd;
    logic [3:0] alu_op;
    logic [2:0] branch_op;
    logic pc_override, rd_write, alu_src_a, alu_src_b, alu_zero, jump, branch_en, branch_pass, system_halt;

    assign rd_write_val = jump ? (pc + 32'd4) : (dmem_read ? dmem_rdata : alu_out);
    reg_file registers(
        .clk(clk),
        .rst(rst),

        .rd(rd),
        .rs1(rs1),
        .rs2(rs2),

        .rd_write(rd_write),
        .rd_write_val(rd_write_val),

        .rv1(rv1),
        .rv2(rv2)
    ); 
    
    bcu branch_control (
        .branch_op(branch_op),
        .rv1(rv1),
        .rv2(rv2),
        .branch(branch_pass)
    );

    assign pc_override = jump | (branch_en & branch_pass);
    pc program_counter(
        .clk(clk),
        .rst(rst),

        .pc_jmp_en(pc_override),
        .pc_jmp_target(alu_out),

        .pc_curr(pc)
    );

    inst_dec instruction_decoder(
        .inst(imem_data),

        .rs1(rs1),
        .rs2(rs2),
        .rd(rd),

        .imm(imm),
        
        .rd_write(rd_write),

        .branch_op(branch_op),
        .mem_width(dmem_width),

        .alu_op(alu_op),
        .alu_src_a(alu_src_a),
        .alu_src_b(alu_src_b),

        .mem_read(dmem_read),
        .mem_write(dmem_write),
        .branch(branch_en),
        .jump(jump),
        .system_halt(system_halt)
    );

    alu arithmetic(
        .alu_in_a(alu_src_a ? pc  : rv1),
        .alu_in_b(alu_src_b ? imm : rv2),
        .alu_op(alu_op),

        .alu_out(alu_out),
        .zero(alu_zero)
    );

    assign imem_addr = pc;
    assign dmem_addr = alu_out;
    assign dmem_wdata = rv2;

    assign debug_pc = pc;
    assign simulation_end = system_halt | (debug_pc == 32'hFF);
endmodule

rtl/soc_top.sv
module soc_top(
    input logic clk,
    input logic rst,
    output logic [31:0] debug_pc,
    output logic simulation_end
);
    logic [31:0] imem_addr, imem_data;
    logic [31:0] dmem_addr, dmem_rdata, dmem_wdata;
    logic dmem_read, dmem_write;
    logic [2:0] dmem_width;

    cpu_top core(
        .clk(clk),
        .rst(rst),

        .imem_addr(imem_addr),
        .imem_data(imem_data),

        .dmem_addr(dmem_addr),
        .dmem_read(dmem_read),
        .dmem_rdata(dmem_rdata),
        .dmem_write(dmem_write),
        .dmem_wdata(dmem_wdata),
        .dmem_width(dmem_width),

        .debug_pc(debug_pc),
        .simulation_end(simulation_end)
    );

    imem instuction_memory(
        .addr(imem_addr),
        .data(imem_data)
    );

    // replace with dbus, in bus/. that then manages MMIO regions, instantiates dmem and peripherals like UART, in peripherals/
    dmem data_memory(
        .clk(clk),

        .mem_read(dmem_read),
        .mem_write(dmem_write),
        .mem_width(dmem_width),

        .addr(dmem_addr),
        .write_data(dmem_wdata),
        .read_data(dmem_rdata)
    );
endmodule

waveform.vcd
$version Generated by VerilatedVcd $end
$date Sun Aug  2 05:31:14 2026
 $end
$timescale   1ps $end

 $scope module TOP $end
  $var wire  1 k clk $end
  $var wire 32 m debug_pc [31:0] $end
  $var wire  1 l rst $end
  $var wire  1 n simulation_end $end
  $scope module soc_top $end
   $var wire  1 k clk $end
   $var wire 32 m debug_pc [31:0] $end
   $var wire 32 ` dmem_addr [31:0] $end
   $var wire 32 a dmem_rdata [31:0] $end
   $var wire  1 E dmem_read $end
   $var wire 32 b dmem_wdata [31:0] $end
   $var wire  3 G dmem_width [2:0] $end
   $var wire  1 F dmem_write $end
   $var wire 32 C imem_addr [31:0] $end
   $var wire 32 D imem_data [31:0] $end
   $var wire  1 l rst $end
   $var wire  1 n simulation_end $end
   $scope module core $end
    $var wire  4 L alu_op [3:0] $end
    $var wire 32 ` alu_out [31:0] $end
    $var wire  1 O alu_src_a $end
    $var wire  1 P alu_src_b $end
    $var wire  1 d alu_zero $end
    $var wire  1 R branch_en $end
    $var wire  3 M branch_op [2:0] $end
    $var wire  1 \ branch_pass $end
    $var wire  1 k clk $end
    $var wire 32 m debug_pc [31:0] $end
    $var wire 32 ` dmem_addr [31:0] $end
    $var wire 32 a dmem_rdata [31:0] $end
    $var wire  1 E dmem_read $end
    $var wire 32 b dmem_wdata [31:0] $end
    $var wire  3 G dmem_width [2:0] $end
    $var wire  1 F dmem_write $end
    $var wire 32 C imem_addr [31:0] $end
    $var wire 32 D imem_data [31:0] $end
    $var wire 32 H imm [31:0] $end
    $var wire  1 Q jump $end
    $var wire 32 C pc [31:0] $end
    $var wire  1 [ pc_override $end
    $var wire  5 K rd [4:0] $end
    $var wire  1 N rd_write $end
    $var wire 32 Z rd_write_val [31:0] $end
    $var wire  5 I rs1 [4:0] $end
    $var wire  5 J rs2 [4:0] $end
    $var wire  1 l rst $end
    $var wire 32 c rv1 [31:0] $end
    $var wire 32 b rv2 [31:0] $end
    $var wire  1 n simulation_end $end
    $var wire  1 S system_halt $end
    $scope module arithmetic $end
     $var wire 32 e alu_in_a [31:0] $end
     $var wire 32 f alu_in_b [31:0] $end
     $var wire  4 L alu_op [3:0] $end
     $var wire 32 ` alu_out [31:0] $end
     $var wire  1 d zero $end
    $upscope $end
    $scope module branch_control $end
     $var wire  1 \ branch $end
     $var wire  3 M branch_op [2:0] $end
     $var wire 32 c rv1 [31:0] $end
     $var wire 32 b rv2 [31:0] $end
    $upscope $end
    $scope module instruction_decoder $end
     $var wire  4 L alu_op [3:0] $end
     $var wire  1 O alu_src_a $end
     $var wire  1 P alu_src_b $end
     $var wire  1 R branch $end
     $var wire  3 M branch_op [2:0] $end
     $var wire  3 U funct3 [2:0] $end
     $var wire  7 V funct7 [6:0] $end
     $var wire 32 H imm [31:0] $end
     $var wire  3 W imm_type [2:0] $end
     $var wire 32 D inst [31:0] $end
     $var wire  1 Q jump $end
     $var wire  1 E mem_read $end
     $var wire  3 G mem_width [2:0] $end
     $var wire  1 F mem_write $end
     $var wire  7 T opcode [6:0] $end
     $var wire  5 K rd [4:0] $end
     $var wire  1 N rd_write $end
     $var wire  5 I rs1 [4:0] $end
     $var wire  5 J rs2 [4:0] $end
     $var wire  1 S system_halt $end
     $scope module immediate_decoder $end
      $var wire 32 H imm [31:0] $end
      $var wire  3 W imm_type [2:0] $end
      $var wire 32 D inst [31:0] $end
     $upscope $end
    $upscope $end
    $scope module program_counter $end
     $var wire 32 o BOOT_ADDR [31:0] $end
     $var wire  1 k clk $end
     $var wire 32 C pc_curr [31:0] $end
     $var wire  1 [ pc_jmp_en $end
     $var wire 32 ` pc_jmp_target [31:0] $end
     $var wire 32 ] pc_next [31:0] $end
     $var wire  1 l rst $end
    $upscope $end
    $scope module registers $end
     $var wire  1 k clk $end
     $var wire  5 K rd [4:0] $end
     $var wire  1 N rd_write $end
     $var wire 32 Z rd_write_val [31:0] $end
     $var wire 32 # registers(0) [31:0] $end
     $var wire 32 $ registers(1) [31:0] $end
     $var wire 32 - registers(10) [31:0] $end
     $var wire 32 . registers(11) [31:0] $end
     $var wire 32 / registers(12) [31:0] $end
     $var wire 32 0 registers(13) [31:0] $end
     $var wire 32 1 registers(14) [31:0] $end
     $var wire 32 2 registers(15) [31:0] $end
     $var wire 32 3 registers(16) [31:0] $end
     $var wire 32 4 registers(17) [31:0] $end
     $var wire 32 5 registers(18) [31:0] $end
     $var wire 32 6 registers(19) [31:0] $end
     $var wire 32 % registers(2) [31:0] $end
     $var wire 32 7 registers(20) [31:0] $end
     $var wire 32 8 registers(21) [31:0] $end
     $var wire 32 9 registers(22) [31:0] $end
     $var wire 32 : registers(23) [31:0] $end
     $var wire 32 ; registers(24) [31:0] $end
     $var wire 32 < registers(25) [31:0] $end
     $var wire 32 = registers(26) [31:0] $end
     $var wire 32 > registers(27) [31:0] $end
     $var wire 32 ? registers(28) [31:0] $end
     $var wire 32 @ registers(29) [31:0] $end
     $var wire 32 & registers(3) [31:0] $end
     $var wire 32 A registers(30) [31:0] $end
     $var wire 32 B registers(31) [31:0] $end
     $var wire 32 ' registers(4) [31:0] $end
     $var wire 32 ( registers(5) [31:0] $end
     $var wire 32 ) registers(6) [31:0] $end
     $var wire 32 * registers(7) [31:0] $end
     $var wire 32 + registers(8) [31:0] $end
     $var wire 32 , registers(9) [31:0] $end
     $var wire  5 I rs1 [4:0] $end
     $var wire  5 J rs2 [4:0] $end
     $var wire  1 l rst $end
     $var wire 32 c rv1 [31:0] $end
     $var wire 32 b rv2 [31:0] $end
    $upscope $end
   $upscope $end
   $scope module data_memory $end
    $var wire 32 ` addr [31:0] $end
    $var wire  2 h addr_byte_offset [1:0] $end
    $var wire 11 g addr_word_index [10:0] $end
    $var wire  1 k clk $end
    $var wire  1 i mem_active $end
    $var wire  1 E mem_read $end
    $var wire  1 _ mem_read_active $end
    $var wire  3 G mem_width [2:0] $end
    $var wire  2 X mem_width_select [1:0] $end
    $var wire  1 Y mem_width_unsigned $end
    $var wire  1 F mem_write $end
    $var wire  1 ^ mem_write_active $end
    $var wire 32 j raw_word [31:0] $end
    $var wire 32 a read_data [31:0] $end
    $var wire 32 b write_data [31:0] $end
   $upscope $end
   $scope module instuction_memory $end
    $var wire 32 C addr [31:0] $end
    $var wire 32 D data [31:0] $end
   $upscope $end
  $upscope $end
 $upscope $end
$enddefinitions $end


#0
b00000000000000000000000000000000 #
b00000000000000000000000000000000 $
b00000000000000000000000000000000 %
b00000000000000000000000000000000 &
b00000000000000000000000000000000 '
b00000000000000000000000000000000 (
b00000000000000000000000000000000 )
b00000000000000000000000000000000 *
b00000000000000000000000000000000 +
b00000000000000000000000000000000 ,
b00000000000000000000000000000000 -
b00000000000000000000000000000000 .
b00000000000000000000000000000000 /
b00000000000000000000000000000000 0
b00000000000000000000000000000000 1
b00000000000000000000000000000000 2
b00000000000000000000000000000000 3
b00000000000000000000000000000000 4
b00000000000000000000000000000000 5
b00000000000000000000000000000000 6
b00000000000000000000000000000000 7
b00000000000000000000000000000000 8
b00000000000000000000000000000000 9
b00000000000000000000000000000000 :
b00000000000000000000000000000000 ;
b00000000000000000000000000000000 <
b00000000000000000000000000000000 =
b00000000000000000000000000000000 >
b00000000000000000000000000000000 ?
b00000000000000000000000000000000 @
b00000000000000000000000000000000 A
b00000000000000000000000000000000 B
b00000000000000000000000000000000 C
b00000000000000000000011100010011 D
0E
0F
b010 G
b00000000000000000000000000000000 H
b00000 I
b00000 J
b01110 K
b0000 L
b000 M
1N
0O
1P
0Q
0R
0S
b0010011 T
b000 U
b0000000 V
b000 W
b10 X
0Y
b00000000000000000000000000000000 Z
0[
1\
b00000000000000000000000000000100 ]
0^
0_
b00000000000000000000000000000000 `
b00000000000000000000000000000000 a
b00000000000000000000000000000000 b
b00000000000000000000000000000000 c
1d
b00000000000000000000000000000000 e
b00000000000000000000000000000000 f
b00000000000 g
b00 h
1i
b00000000000000000000000000000000 j
1k
1l
b00000000000000000000000000000000 m
0n
b00000000000000000000000000000000 o
#1
#2
#3
#4
#5
0k
#6
#7
#8
#9
#10
1k
#11
0l
#12
#13
#14
#15
0k
#16
#17
#18
#19
#20
b00000000000000000000000000000100 C
b00000000000100000000011110010011 D
b00000000000000000000000000000001 H
b00001 J
b01111 K
b00000000000000000000000000000001 Z
b00000000000000000000000000001000 ]
b00000000000000000000000000000001 `
0d
b00000000000000000000000000000001 f
b01 h
1k
b00000000000000000000000000000100 m
#21
#22
#23
#24
#25
b00000000000000000000000000000001 2
0k
#26
#27
#28
#29
#30
b00000000000000000000000000001000 C
b00000100000100000000011010010011 D
b00000000000000000000000001000001 H
b01101 K
b0000010 V
b00000000000000000000000001000001 Z
b00000000000000000000000000001100 ]
b00000000000000000000000001000001 `
b00000000000000000000000001000001 f
b00000010000 g
1k
b00000000000000000000000000001000 m
#31
#32
#33
#34
#35
b00000000000000000000000001000001 0
0k
#36
#37
#38
#39
#40
b00000000000000000000000000001100 C
b00000000111101110010000000100011 D
1F
b00000000000000000000000000000000 H
b01110 I
b01111 J
b00000 K
0N
b0100011 T
b010 U
b0000000 V
b001 W
b00000000000000000000000000000000 Z
0\
b00000000000000000000000000010000 ]
1^
b00000000000000000000000000000000 `
b00000000000000000000000000000001 b
1d
b00000000000000000000000000000000 f
b00000000000 g
b00 h
1k
b00000000000000000000000000001100 m
#41
#42
#43
#44
#45
b00000000000000000000000000000001 j
0k
#46
#47
#48
#49
#50
b00000000000000000000000000010000 C
b00000000000101111000011110010011 D
0F
b00000000000000000000000000000001 H
b01111 I
b00001 J
b01111 K
1N
b0010011 T
b000 U
b000 W
b00000000000000000000000000000010 Z
b00000000000000000000000000010100 ]
0^
b00000000000000000000000000000010 `
b00000000000000000000000000000000 b
b00000000000000000000000000000001 c
0d
b00000000000000000000000000000001 e
b00000000000000000000000000000001 f
b10 h
1k
b00000000000000000000000000010000 m
#51
#52
#53
#54
#55
b00000000000000000000000000000010 2
b00000000000000000000000000000011 Z
b00000000000000000000000000000011 `
b00000000000000000000000000000010 c
b00000000000000000000000000000010 e
b11 h
0k
#56
#57
#58
#59
#60
b00000000000000000000000000010100 C
b00000000010001110000011100010011 D
b00000000000000000000000000000100 H
b01110 I
b00100 J
b01110 K
b00000000000000000000000000000100 Z
1\
b00000000000000000000000000011000 ]
b00000000000000000000000000000100 `
b00000000000000000000000000000000 c
b00000000000000000000000000000000 e
b00000000000000000000000000000100 f
b00000000001 g
b00 h
b00000000000000000000000000000000 j
1k
b00000000000000000000000000010100 m
#61
#62
#63
#64
#65
b00000000000000000000000000000100 1
b00000000000000000000000000001000 Z
0\
b00000000000000000000000000001000 `
b00000000000000000000000000000100 c
b00000000000000000000000000000100 e
b00000000010 g
0k
#66
#67
#68
#69
#70
b00000000000000000000000000011000 C
b11111110110101111001101011100011 D
b11111111111111111111111111110100 H
b01111 I
b01101 J
b10101 K
b001 M
0N
1O
1R
b1100011 T
b001 U
b1111111 V
b010 W
b00000000000000000000000000001100 Z
1[
1\
b00000000000000000000000000001100 ]
b00000000000000000000000000001100 `
b00000000000000000000000001000001 b
b00000000000000000000000000000010 c
b00000000000000000000000000011000 e
b11111111111111111111111111110100 f
b00000000011 g
1k
b00000000000000000000000000011000 m
#71
#72
#73
#74
#75
0k
#76
#77
#78
#79
#80
b00000000000000000000000000001100 C
b00000000111101110010000000100011 D
1F
b00000000000000000000000000000000 H
b01110 I
b01111 J
b00000 K
b000 M
0O
0R
b0100011 T
b010 U
b0000000 V
b001 W
b00000000000000000000000000000100 Z
0[
0\
b00000000000000000000000000010000 ]
1^
b00000000000000000000000000000100 `
b00000000000000000000000000000010 b
b00000000000000000000000000000100 c
b00000000000000000000000000000100 e
b00000000000000000000000000000000 f
b00000000001 g
1k
b00000000000000000000000000001100 m
#81
#82
#83
#84
#85
b00000000000000000000000000000010 j
0k
#86
#87
#88
#89
#90
b00000000000000000000000000010000 C
b00000000000101111000011110010011 D
0F
b00000000000000000000000000000001 H
b01111 I
b00001 J
b01111 K
1N
b0010011 T
b000 U
b000 W
b00000000000000000000000000000011 Z
b00000000000000000000000000010100 ]
0^
b00000000000000000000000000000011 `
b00000000000000000000000000000000 b
b00000000000000000000000000000010 c
b00000000000000000000000000000010 e
b00000000000000000000000000000001 f
b00000000000 g
b11 h
b00000000000000000000000000000001 j
1k
b00000000000000000000000000010000 m
#91
#92
#93
#94
#95
b00000000000000000000000000000011 2
b00000000000000000000000000000100 Z
b00000000000000000000000000000100 `
b00000000000000000000000000000011 c
b00000000000000000000000000000011 e
b00000000001 g
b00 h
b00000000000000000000000000000010 j
0k
#96
#97
#98
#99
#100
b00000000000000000000000000010100 C
b00000000010001110000011100010011 D
b00000000000000000000000000000100 H
b01110 I
b00100 J
b01110 K
b00000000000000000000000000001000 Z
b00000000000000000000000000011000 ]
b00000000000000000000000000001000 `
b00000000000000000000000000000100 c
b00000000000000000000000000000100 e
b00000000000000000000000000000100 f
b00000000010 g
b00000000000000000000000000000000 j
1k
b00000000000000000000000000010100 m
#101
#102
#103
#104
#105
b00000000000000000000000000001000 1
b00000000000000000000000000001100 Z
b00000000000000000000000000001100 `
b00000000000000000000000000001000 c
b00000000000000000000000000001000 e
b00000000011 g
0k
#106
#107
#108
#109
#110
b00000000000000000000000000011000 C
b11111110110101111001101011100011 D
b11111111111111111111111111110100 H
b01111 I
b01101 J
b10101 K
b001 M
0N
1O
1R
b1100011 T
b001 U
b1111111 V
b010 W
1[
1\
b00000000000000000000000000001100 ]
b00000000000000000000000001000001 b
b00000000000000000000000000000011 c
b00000000000000000000000000011000 e
b11111111111111111111111111110100 f
1k
b00000000000000000000000000011000 m
#111
#112
#113
#114
#115
0k
#116
#117
#118
#119
#120
b00000000000000000000000000001100 C
b00000000111101110010000000100011 D
1F
b00000000000000000000000000000000 H
b01110 I
b01111 J
b00000 K
b000 M
0O
0R
b0100011 T
b010 U
b0000000 V
b001 W
b00000000000000000000000000001000 Z
0[
0\
b00000000000000000000000000010000 ]
1^
b00000000000000000000000000001000 `
b00000000000000000000000000000011 b
b00000000000000000000000000001000 c
b00000000000000000000000000001000 e
b00000000000000000000000000000000 f
b00000000010 g
1k
b00000000000000000000000000001100 m
#121
#122
#123
#124
#125
b00000000000000000000000000000011 j
0k
#126
#127
#128
#129
#130
b00000000000000000000000000010000 C
b00000000000101111000011110010011 D
0F
b00000000000000000000000000000001 H
b01111 I
b00001 J
b01111 K
1N
b0010011 T
b000 U
b000 W
b00000000000000000000000000000100 Z
b00000000000000000000000000010100 ]
0^
b00000000000000000000000000000100 `
b00000000000000000000000000000000 b
b00000000000000000000000000000011 c
b00000000000000000000000000000011 e
b00000000000000000000000000000001 f
b00000000001 g
b00000000000000000000000000000010 j
1k
b00000000000000000000000000010000 m
#131
#132
#133
#134
#135
b00000000000000000000000000000100 2
b00000000000000000000000000000101 Z
b00000000000000000000000000000101 `
b00000000000000000000000000000100 c
b00000000000000000000000000000100 e
b01 h
0k
#136
#137
#138
#139
#140
b00000000000000000000000000010100 C
b00000000010001110000011100010011 D
b00000000000000000000000000000100 H
b01110 I
b00100 J
b01110 K
b00000000000000000000000000001100 Z
b00000000000000000000000000011000 ]
b00000000000000000000000000001100 `
b00000000000000000000000000001000 c
b00000000000000000000000000001000 e
b00000000000000000000000000000100 f
b00000000011 g
b00 h
b00000000000000000000000000000000 j
1k
b00000000000000000000000000010100 m
#141
#142
#143
#144
#145
b00000000000000000000000000001100 1
b00000000000000000000000000010000 Z
b00000000000000000000000000010000 `
b00000000000000000000000000001100 c
b00000000000000000000000000001100 e
b00000000100 g
0k
#146
#147
#148
#149
#150
b00000000000000000000000000011000 C
b11111110110101111001101011100011 D
b11111111111111111111111111110100 H
b01111 I
b01101 J
b10101 K
b001 M
0N
1O
1R
b1100011 T
b001 U
b1111111 V
b010 W
b00000000000000000000000000001100 Z
1[
1\
b00000000000000000000000000001100 ]
b00000000000000000000000000001100 `
b00000000000000000000000001000001 b
b00000000000000000000000000000100 c
b00000000000000000000000000011000 e
b11111111111111111111111111110100 f
b00000000011 g
1k
b00000000000000000000000000011000 m
#151
#152
#153
#154
#155
0k
#156
#157
#158
#159
